ok_py_logging.py
ok_py_logging-0.1.dist-info/METADATA
ok_py_logging-0.1.dist-info/WHEEL
ok_py_logging-0.1.dist-info/licenses/LICENSE
ok_py_logging-0.1.dist-info/RECORD
