Metadata-Version: 2.4
Name: ok-py-logging
Version: 0.1
Summary: Simple minimalist Python logging defaults
Project-URL: Homepage, https://github.com/egnor/ok-py-logging#readme
Project-URL: Repository, https://github.com/egnor/ok-py-logging.git
Author-email: Dan Egnor <egnor@ofb.net>
License-File: LICENSE
Requires-Python: >=3.9
